[
    {
                "id": "987654",
                "keys": {
                    "pixel": "821579541228161",
                    "token": "EAAHsZAFn3hq4BAKyU1uiACRaHyZCVqQwiH194DAFxZA8VoLy3ZBmevsPK5RgeSscLxixOwFshE8UbcEGkJwvMe5I0nutL8JhHM3TNTnTcZC65d3Sh2Xsh9na94zoXmI8CBFY643TfJzZAIzxGkfs4URA83I1AqN1IizO5G74XTdcCyObZAZAGK7h",
                    "active": true
        }
    },
    {
                "id": "12345",
                "keys": {
                    "pixel": "821579541228161",
                    "token": "",
                    "active": true
        }
    },
    {
                "id": "56789",
                "keys": {
                    "pixel": "821579541228161",
                    "token": "",
                    "active": true
        }
    },
    {
                "id": "23456",
                "keys": {
                    "pixel": "821579541228161",
                    "token": "",
                    "active": true
        }
    },
    {
                "id": "34567",
                "keys": {
                    "pixel": "821579541228161",
                    "token": "",
                    "active": true
        }
    }
]